connectedcar/__init__.py
connectedcar/api.py
connectedcar/connectedcar.py
connectedcar/const.py
connectedcar/exceptions.py
connectedcar/requester.py
connectedcar/user.py
connectedcar/vehicle.py
connectedcar-1.3.10.dist-info/LICENSE
connectedcar-1.3.10.dist-info/METADATA
connectedcar-1.3.10.dist-info/WHEEL
connectedcar-1.3.10.dist-info/top_level.txt
connectedcar-1.3.10.dist-info/RECORD
