Metadata-Version: 2.1
Name: connectedcar
Version: 1.3.10
Summary: ConnectedCar SDK
Home-page: https://github.com/ianjwhite99/connected-car-python-sdk
Author: Ian White
Author-email: iwhite99@protonmail.com
License: MIT
Provides-Extra: dev
License-File: LICENSE
